{
  "type": "FeatureCollection",
  "features": [
    {
      "type": "Feature",
      "id": "BU03920600",
      "geometry": {
        "type": "Polygon",
        "coordinates": [
          [
            [
              4.624751779067947,
              52.39932828452432
            ],
            [
              4.6288784753870855,
              52.39819692009304
            ],
            [
              4.629488294888138,
              52.399056734881945
            ],
            [
              4.630180434542664,
              52.399232795452114
            ],
            [
              4.631826373305611,
              52.398710160390344
            ],
            [
              4.637895878100035,
              52.397468675076745
            ],
            [
              4.638181562117712,
              52.39665081161131
            ],
            [
              4.641013439893484,
              52.39593526662812
            ],
            [
              4.639400773693244,
              52.39371832033556
            ],
            [
              4.635758514663421,
              52.39448430204333
            ],
            [
              4.634306947076598,
              52.392309880765865
            ],
            [
              4.634526612332132,
              52.39123148940734
            ],
            [
              4.633092120602235,
              52.39143471854132
            ],
            [
              4.631819218239127,
              52.39128895748213
            ],
            [
              4.631490108573081,
              52.39068460112288
            ],
            [
              4.631684657161083,
              52.390045947434075
            ],
            [
              4.630220601509331,
              52.38991861148524
            ],
            [
              4.627946574236344,
              52.39041191415192
            ],
            [
              4.625723073846605,
              52.39138837017051
            ],
            [
              4.624990037358114,
              52.39197607446402
            ],
            [
              4.624078760590205,
              52.393347185928015
            ],
            [
              4.624262710303599,
              52.393597251720166
            ],
            [
              4.623629901114672,
              52.39501987423673
            ],
            [
              4.623685944133677,
              52.3960306420472
            ],
            [
              4.624078723694344,
              52.39779948973932
            ],
            [
              4.624731249027151,
              52.399333770302924
            ]
          ]
        ]
      },
      "bbox": [
        103003.3984375,
        489210.6875,
        104187.5,
        490262.03125
      ]
    }
  ],
  "bbox": [
    103003.3984375,
    489210.6875,
    104187.5,
    490262.03125
  ]
}
