{
  "type": "FeatureCollection",
  "features": [
    {
      "type": "Feature",
      "id": "BU03560005",
      "geometry": {
        "type": "Polygon",
        "coordinates": [
          [
            [
              5.084562987147851,
              52.02629361237213
            ],
            [
              5.081735412774636,
              52.023141209199984
            ],
            [
              5.0760546816858065,
              52.0174457043766
            ],
            [
              5.0754309907296955,
              52.017208366313504
            ],
            [
              5.07076369858617,
              52.01941285375329
            ],
            [
              5.068505182745122,
              52.02010706636024
            ],
            [
              5.066317785648001,
              52.02036657768774
            ],
            [
              5.063644467958622,
              52.02560893664026
            ],
            [
              5.063330668229758,
              52.02681037613124
            ],
            [
              5.067091134222427,
              52.02861036556723
            ],
            [
              5.068738220212825,
              52.02920278732732
            ],
            [
              5.075156892990083,
              52.02997312380019
            ],
            [
              5.0859816859392115,
              52.02758523667279
            ]
          ]
        ]
      },
      "bbox": [
        132744.96875,
        447523.625,
        134299.703125,
        448943.71875
      ]
    }
  ],
  "bbox": [
    132744.96875,
    447523.625,
    134299.703125,
    448943.71875
  ]
}
