{
  "type": "FeatureCollection",
  "features": [
    {
      "type": "Feature",
      "id": "BU05992308",
      "geometry": {
        "type": "Polygon",
        "coordinates": [
          [
            [
              4.081133859162109,
              51.983485539153705
            ],
            [
              4.078907437831985,
              51.98066961405174
            ],
            [
              4.10024880702009,
              51.97491177810267
            ],
            [
              4.098382249857934,
              51.97223922971397
            ],
            [
              4.096524169111322,
              51.971796869557785
            ],
            [
              4.094786181521063,
              51.971012206316544
            ],
            [
              4.093496823347889,
              51.969968648624736
            ],
            [
              4.092879869637504,
              51.969103575624615
            ],
            [
              4.0907321609414655,
              51.96299888405585
            ],
            [
              4.090771096151758,
              51.96274927345717
            ],
            [
              4.091271361557373,
              51.96267443971213
            ],
            [
              4.09087544138954,
              51.96156989814072
            ],
            [
              4.090738378009349,
              51.96140684379899
            ],
            [
              4.089926172287101,
              51.961307980994356
            ],
            [
              4.088576933874674,
              51.95971502036226
            ],
            [
              4.083174313528989,
              51.94442941576919
            ],
            [
              4.085351061794612,
              51.942291679238394
            ],
            [
              4.1068340231335965,
              51.93955391857178
            ],
            [
              4.107381981111843,
              51.9394503196883
            ],
            [
              4.106973439990002,
              51.93825550980279
            ],
            [
              4.113335618460401,
              51.93736101650481
            ],
            [
              4.112924874439676,
              51.93633898457191
            ],
            [
              4.107972026208161,
              51.93768230265316
            ],
            [
              4.1062223598699115,
              51.93492487949723
            ],
            [
              4.105869950149222,
              51.93483928225915
            ],
            [
              4.10196747278907,
              51.928548455740746
            ],
            [
              4.102250274901883,
              51.925069521016326
            ],
            [
              4.093140003067913,
              51.93406764715862
            ],
            [
              4.086941345165686,
              51.934872954422254
            ],
            [
              4.083083119039743,
              51.93521143851285
            ],
            [
              4.078355588146401,
              51.93533334056051
            ],
            [
              4.073960771745085,
              51.93516827383037
            ],
            [
              4.069112173727402,
              51.93465828934003
            ],
            [
              4.064177436090996,
              51.93376673286651
            ],
            [
              3.9960301904677804,
              51.917915938288054
            ],
            [
              3.9960252192193595,
              51.91807461629837
            ],
            [
              3.9968972715424056,
              51.918164449545706
            ],
            [
              3.9969055607483805,
              51.91837554123821
            ],
            [
              3.993397160234097,
              51.91923806407851
            ],
            [
              3.9937054759730404,
              51.91869864487059
            ],
            [
              3.9945576009609045,
              51.918158368461825
            ],
            [
              3.9957020901637446,
              51.91783928607555
            ],
            [
              3.9949853865062956,
              51.91767205715527
            ],
            [
              3.993780921162659,
              51.9181797816906
            ],
            [
              3.9946551979638687,
              51.91759509628808
            ],
            [
              3.9936122169762736,
              51.91735150537335
            ],
            [
              3.9929783134589956,
              51.918128958763134
            ],
            [
              3.992580169761933,
              51.91917245851895
            ],
            [
              3.987952166618003,
              51.92227081284514
            ],
            [
              3.9879575648650407,
              51.92301455306865
            ],
            [
              3.988531118912684,
              51.92439157820861
            ],
            [
              3.989830512261807,
              51.926230970163346
            ],
            [
              3.9941781726552015,
              51.93105537858913
            ],
            [
              4.004746356657132,
              51.94053665007746
            ],
            [
              4.00915632535675,
              51.944755197634834
            ],
            [
              4.013530846291629,
              51.94976318251895
            ],
            [
              4.015069448124245,
              51.952003735553276
            ],
            [
              4.015843431588623,
              51.95403643669241
            ],
            [
              4.016308837910117,
              51.95732867404596
            ],
            [
              4.016176717374314,
              51.957686465178
            ],
            [
              4.01589193079045,
              51.95781125521841
            ],
            [
              4.014043147231311,
              51.96166422216317
            ],
            [
              4.013205111587107,
              51.96224666739683
            ],
            [
              4.009496428627316,
              51.96200828196956
            ],
            [
              4.00870844731327,
              51.96216957947338
            ],
            [
              4.007410081551417,
              51.96284632147756
            ],
            [
              4.006931040281726,
              51.963547562739784
            ],
            [
              4.006310534710861,
              51.966795618939614
            ],
            [
              4.006429497440349,
              51.97010630029236
            ],
            [
              4.007149805314878,
              51.97284388324807
            ],
            [
              4.008521095740392,
              51.97561606616298
            ],
            [
              4.011078277446512,
              51.97901795205443
            ],
            [
              4.013717985581167,
              51.98151890203154
            ],
            [
              4.016816997394678,
              51.98372509201637
            ],
            [
              4.020328583552356,
              51.98570308896535
            ],
            [
              4.0237664786739336,
              51.987190996398986
            ],
            [
              4.026740453126093,
              51.98816885623122
            ],
            [
              4.029178709629438,
              51.98871538351386
            ],
            [
              4.031751733001037,
              51.98897937702871
            ],
            [
              4.033740433543411,
              51.98902672413818
            ],
            [
              4.035975380752733,
              51.988860820150265
            ],
            [
              4.041934291859919,
              51.98751401630865
            ],
            [
              4.045841357901236,
              51.99346439022182
            ],
            [
              4.082571294445094,
              51.98567684048588
            ]
          ]
        ]
      },
      "bbox": [
        58729.01953125,
        437288.78125,
        67381.734375,
        445687.28125
      ]
    }
  ],
  "bbox": [
    58729.01953125,
    437288.78125,
    67381.734375,
    445687.28125
  ]
}
