{
  "type": "FeatureCollection",
  "features": [
    {
      "type": "Feature",
      "id": "BU06320104",
      "geometry": {
        "type": "Polygon",
        "coordinates": [
          [
            [
              4.894424757262504,
              52.09719854099347
            ],
            [
              4.896860431563028,
              52.096092928843284
            ],
            [
              4.898117920973039,
              52.095725951164745
            ],
            [
              4.900734545591164,
              52.09548397075031
            ],
            [
              4.902326613595373,
              52.095497560593984
            ],
            [
              4.903952668475446,
              52.096037415454916
            ],
            [
              4.905968405018398,
              52.09750697196367
            ],
            [
              4.907763950877462,
              52.09851040799186
            ],
            [
              4.9086456682475585,
              52.0987095090235
            ],
            [
              4.910505301522413,
              52.09864401551927
            ],
            [
              4.9102110564835595,
              52.098103755386255
            ],
            [
              4.914101544352237,
              52.093590601224356
            ],
            [
              4.899899147131155,
              52.08881167425449
            ],
            [
              4.896056066623665,
              52.08770717103724
            ],
            [
              4.892052027876072,
              52.08624847754269
            ],
            [
              4.891100359405647,
              52.087398457675036
            ],
            [
              4.891736787428801,
              52.08799891848597
            ],
            [
              4.891443362829476,
              52.088418208453895
            ],
            [
              4.894014981443599,
              52.08965659417131
            ],
            [
              4.8949955262714075,
              52.09034303240377
            ],
            [
              4.89555275542911,
              52.09162182369251
            ],
            [
              4.8951277058408476,
              52.092833586568595
            ],
            [
              4.89280945630019,
              52.09584816983569
            ],
            [
              4.893080149736047,
              52.096672657918
            ],
            [
              4.892810754296387,
              52.096812544691446
            ],
            [
              4.893695258485569,
              52.097328356892724
            ],
            [
              4.89449260645099,
              52.09730163853245
            ]
          ]
        ]
      },
      "bbox": [
        120972.1953125,
        455273.9375,
        122552.9453125,
        456652.53125
      ]
    }
  ],
  "bbox": [
    120972.1953125,
    455273.9375,
    122552.9453125,
    456652.53125
  ]
}
