{
  "type": "FeatureCollection",
  "features": [
    {
      "type": "Feature",
      "id": "BU07580900",
      "geometry": {
        "type": "Polygon",
        "coordinates": [
          [
            [
              4.71838407549581,
              51.61172296770307
            ],
            [
              4.7238396527477375,
              51.60415989688645
            ],
            [
              4.7263258023324095,
              51.601917814461466
            ],
            [
              4.728351277685569,
              51.60053442190978
            ],
            [
              4.732306582917545,
              51.59858591406886
            ],
            [
              4.735369597814474,
              51.597410481904866
            ],
            [
              4.738661294699157,
              51.59644525289231
            ],
            [
              4.74335297981049,
              51.595398036355505
            ],
            [
              4.742745585255164,
              51.59494098285803
            ],
            [
              4.748594687167936,
              51.59424154764458
            ],
            [
              4.74587319581721,
              51.59435165762889
            ],
            [
              4.737434517234951,
              51.5938712795757
            ],
            [
              4.737554466155488,
              51.59403067320424
            ],
            [
              4.70341719650774,
              51.59159293388598
            ],
            [
              4.703787191041729,
              51.59351246671656
            ],
            [
              4.702177382213619,
              51.593708964900664
            ],
            [
              4.703560064375384,
              51.59838195476544
            ],
            [
              4.701475380498216,
              51.5984840808493
            ],
            [
              4.701575375788879,
              51.599358650080916
            ],
            [
              4.706917892876738,
              51.599169619749006
            ],
            [
              4.706961373594874,
              51.599323262179894
            ],
            [
              4.699397343438534,
              51.604442256965754
            ],
            [
              4.6987715132889445,
              51.606393022564234
            ],
            [
              4.699893285025434,
              51.606322929825886
            ],
            [
              4.7000898723789675,
              51.60659883801198
            ],
            [
              4.707658832239879,
              51.60910546370309
            ],
            [
              4.708606588751237,
              51.60976722841731
            ],
            [
              4.7093075176840955,
              51.61068067425333
            ],
            [
              4.709734115530083,
              51.61052385884012
            ],
            [
              4.7099086773854815,
              51.610746526204
            ],
            [
              4.712669532499066,
              51.61140638834715
            ],
            [
              4.7182915426504195,
              51.61185503823123
            ]
          ]
        ]
      },
      "bbox": [
        107285.1640625,
        400353.78125,
        110724.2734375,
        402598.09375
      ]
    }
  ],
  "bbox": [
    107285.1640625,
    400353.78125,
    110724.2734375,
    402598.09375
  ]
}
