{
  "type": "FeatureCollection",
  "features": [
    {
      "type": "Feature",
      "id": "BU07180602",
      "geometry": {
        "type": "Polygon",
        "coordinates": [
          [
            [
              3.6171088762283103,
              51.47171156351772
            ],
            [
              3.620053417448502,
              51.47357164163338
            ],
            [
              3.6229012504371187,
              51.474738678943254
            ],
            [
              3.636824340509695,
              51.47830642611516
            ],
            [
              3.6423328868198364,
              51.474924701839015
            ],
            [
              3.6422544493079605,
              51.474755501086804
            ],
            [
              3.646456092427911,
              51.472302350760714
            ],
            [
              3.648536138800653,
              51.47133166673116
            ],
            [
              3.6519061444474175,
              51.470358786801334
            ],
            [
              3.6554695359614255,
              51.46978570926621
            ],
            [
              3.6588356115389824,
              51.46962882531824
            ],
            [
              3.661961746296539,
              51.469832729330555
            ],
            [
              3.6567384811527615,
              51.465181263362716
            ],
            [
              3.65484996075075,
              51.46454350180008
            ],
            [
              3.655734666494787,
              51.46283674626482
            ],
            [
              3.6550988178974237,
              51.46248282222696
            ],
            [
              3.644590418354516,
              51.45999836556983
            ],
            [
              3.637139898724736,
              51.458581369730474
            ],
            [
              3.6306497254326393,
              51.458082846464166
            ],
            [
              3.6253418540102906,
              51.45802161597817
            ],
            [
              3.6090756011615257,
              51.46214746296744
            ],
            [
              3.609953936765722,
              51.46249072523223
            ],
            [
              3.611942669390371,
              51.46367473275653
            ],
            [
              3.6165810940959893,
              51.47112275971183
            ]
          ]
        ]
      },
      "bbox": [
        31422.19921875,
        386750.90625,
        35116.58203125,
        388989.78125
      ]
    }
  ],
  "bbox": [
    31422.19921875,
    386750.90625,
    35116.58203125,
    388989.78125
  ]
}
