{
  "type": "FeatureCollection",
  "features": [
    {
      "type": "Feature",
      "id": "BU15090101",
      "geometry": {
        "type": "Polygon",
        "coordinates": [
          [
            [
              6.389990523261079,
              51.8403067886209
            ],
            [
              6.390382867141721,
              51.84136790305105
            ],
            [
              6.38961953213501,
              51.84274257873982
            ],
            [
              6.38976162894688,
              51.84319704333375
            ],
            [
              6.391136011105769,
              51.84377161422428
            ],
            [
              6.3948861123955325,
              51.84155296986988
            ],
            [
              6.398292865444349,
              51.83989481809267
            ],
            [
              6.398581860433792,
              51.83957599520874
            ],
            [
              6.397605053485855,
              51.83653568558144
            ],
            [
              6.389756195365958,
              51.83695020165703
            ],
            [
              6.389898324383794,
              51.838986334875784
            ],
            [
              6.388456565401766,
              51.83915820915829
            ],
            [
              6.3887518101907865,
              51.84023982232702
            ],
            [
              6.389974212916013,
              51.84007318933402
            ]
          ]
        ]
      },
      "bbox": [
        223965.359375,
        427862.1875,
        224662.40625,
        428660.90625
      ]
    }
  ],
  "bbox": [
    223965.359375,
    427862.1875,
    224662.40625,
    428660.90625
  ]
}
