{
  "type": "FeatureCollection",
  "features": [
    {
      "type": "Feature",
      "id": "BU16630300",
      "geometry": {
        "type": "Polygon",
        "coordinates": [
          [
            [
              6.3940668888016,
              53.394278957142234
            ],
            [
              6.39487379132946,
              53.39413740811966
            ],
            [
              6.397460993611408,
              53.392521164343734
            ],
            [
              6.400451038200907,
              53.38989553093528
            ],
            [
              6.400605324718419,
              53.38942524177181
            ],
            [
              6.400383032239026,
              53.38854361243311
            ],
            [
              6.398920355752912,
              53.38720229720372
            ],
            [
              6.394282473099921,
              53.38506303944015
            ],
            [
              6.391394819237925,
              53.385374731664
            ],
            [
              6.389430665755839,
              53.385970736495786
            ],
            [
              6.388344185720922,
              53.386567277456294
            ],
            [
              6.387161047186728,
              53.38791780374428
            ],
            [
              6.390574876769797,
              53.39224342794953
            ],
            [
              6.3924853194010165,
              53.39383104487656
            ],
            [
              6.393242830414339,
              53.39420945837354
            ]
          ]
        ]
      },
      "bbox": [
        221494.90625,
        600136.3125,
        222386.90625,
        601161.625
      ]
    }
  ],
  "bbox": [
    221494.90625,
    600136.3125,
    222386.90625,
    601161.625
  ]
}
