{
  "type": "FeatureCollection",
  "features": [
    {
      "type": "Feature",
      "id": "BU18950002",
      "geometry": {
        "type": "Polygon",
        "coordinates": [
          [
            [
              7.052759905574738,
              53.154780438061564
            ],
            [
              7.050058020551076,
              53.15240510988938
            ],
            [
              7.045578094583081,
              53.15322668178837
            ],
            [
              7.041318148214381,
              53.15424560354363
            ],
            [
              7.0357661512327105,
              53.154987212001004
            ],
            [
              7.03284352113287,
              53.155042529224936
            ],
            [
              7.027162469002717,
              53.15428220181081
            ],
            [
              7.023931727623792,
              53.161270419735466
            ],
            [
              7.023782040622313,
              53.16193479190034
            ],
            [
              7.024210085436115,
              53.16313282621813
            ],
            [
              7.02962988777176,
              53.16245930506533
            ],
            [
              7.0387945501247335,
              53.160917759030426
            ],
            [
              7.042172202954742,
              53.16019930704006
            ],
            [
              7.04819011435455,
              53.158601550957066
            ],
            [
              7.0548351780694984,
              53.1565301772652
            ]
          ]
        ]
      },
      "bbox": [
        264414.40625,
        575060.375,
        266504.6875,
        576214.3125
      ]
    }
  ],
  "bbox": [
    264414.40625,
    575060.375,
    266504.6875,
    576214.3125
  ]
}
