{
  "type": "FeatureCollection",
  "features": [
    {
      "type": "Feature",
      "id": "WK037503",
      "geometry": {
        "type": "Polygon",
        "coordinates": [
          [
            [
              4.657900646410908,
              52.49105873665427
            ],
            [
              4.65310762721383,
              52.48829939860105
            ],
            [
              4.651405118692506,
              52.4877028913746
            ],
            [
              4.646161704563909,
              52.49087496664707
            ],
            [
              4.656125028573724,
              52.49726542277696
            ],
            [
              4.658656038616765,
              52.49802425571622
            ],
            [
              4.660438178057217,
              52.49140156758892
            ]
          ]
        ]
      },
      "bbox": [
        104646.015625,
        500074.3125,
        105616.1015625,
        501217.59375
      ]
    }
  ],
  "bbox": [
    104646.015625,
    500074.3125,
    105616.1015625,
    501217.59375
  ]
}
